MarsGT/__init__.py
MarsGT/conv.py
MarsGT/egrn.py
MarsGT/marsgt_model.py
MarsGT/utils.py
MarsGT-0.2.1.dist-info/METADATA
MarsGT-0.2.1.dist-info/WHEEL
MarsGT-0.2.1.dist-info/top_level.txt
MarsGT-0.2.1.dist-info/RECORD
